fyerstest/__init__.py
fyerstest/fyersApi.py
fyerstest/hsmFyers.py
fyerstest/ws.py
FyersTestSDK-0.0.4.dist-info/LICENSE.txt
FyersTestSDK-0.0.4.dist-info/METADATA
FyersTestSDK-0.0.4.dist-info/WHEEL
FyersTestSDK-0.0.4.dist-info/top_level.txt
FyersTestSDK-0.0.4.dist-info/RECORD
