Metadata-Version: 2.1
Name: FyersTestSDK
Version: 0.0.4
Summary: Fyers trading APIs.
Home-page: https://github.com/
Author: Fyers-Tech
Author-email: support@fyers.in
License: UNKNOWN
Platform: UNKNOWN
Classifier: Programming Language :: Python :: 3
Classifier: License :: OSI Approved :: MIT License
Classifier: Operating System :: OS Independent
License-File: LICENSE.txt
Requires-Dist: asyncio (==3.4.3)
Requires-Dist: aiohttp (==3.8.4)
Requires-Dist: cryptography (==3.4.8)
Requires-Dist: Requests (==2.30.0)
Requires-Dist: websocket-client (==1.2.1)
Requires-Dist: websockets (==8.1)
